dot_tools/__init__.py
dot_tools/resources/traefik.compose.yaml
dot_tools/scripts/__init__.py
dot_tools/scripts/add_dot_files.py
dot_tools/scripts/cpuniq.py
dot_tools/scripts/handle_envrc.py
dot_tools/scripts/release.py
dot_tools/scripts/traefik_run.py
dot_tools/templates/editorconfig.tmpl
dot_tools/templates/pre-commit-config.yaml
dot_tools/templates/projectile.tmpl
dot_tools/templates/pyproject.tmpl
dot_tools/templates/yamllint.tmpl
dot_tools-1.6.0.dist-info/METADATA
dot_tools-1.6.0.dist-info/WHEEL
dot_tools-1.6.0.dist-info/entry_points.txt
dot_tools-1.6.0.dist-info/licenses/LICENSE
dot_tools-1.6.0.dist-info/RECORD
