Metadata-Version: 2.4
Name: dot-tools
Version: 1.6.0
Summary: Dot files automation
Project-URL: github, https://github.com/cybergrind/dot-tools
Author-email: cybergrind <cybergrind+pypi@gmail.com>
License-Expression: MIT
License-File: LICENSE
Requires-Dist: fan-tools>=3.7.0
